sqlalchemy_jsonfield/__init__.py
sqlalchemy_jsonfield/_version.py
sqlalchemy_jsonfield/jsonfield.py
SQLAlchemy_JSONField-1.0.1.post0.dist-info/LICENSE
SQLAlchemy_JSONField-1.0.1.post0.dist-info/METADATA
SQLAlchemy_JSONField-1.0.1.post0.dist-info/WHEEL
SQLAlchemy_JSONField-1.0.1.post0.dist-info/top_level.txt
SQLAlchemy_JSONField-1.0.1.post0.dist-info/RECORD
