Metadata-Version: 2.1
Name: SQLAlchemy-JSONField
Version: 1.0.1.post0
Summary: SQLALchemy JSONField implementation for storing dicts at SQL
Author-email: Alexey Stepanov <penguinolog@gmail.com>
License: Apache License, Version 2.0
Project-URL: Bug Tracker, https://github.com/penguinolog/sqlalchemy_jsonfield/issues
Keywords: sql,sqlalchemy,json,jsonfield,development
Classifier: Development Status :: 4 - Beta
Classifier: Intended Audience :: Developers
Classifier: Topic :: Software Development :: Libraries :: Python Modules
Classifier: License :: OSI Approved :: Apache Software License
Classifier: Programming Language :: Python :: 3
Classifier: Programming Language :: Python :: 3.7
Classifier: Programming Language :: Python :: 3.8
Classifier: Programming Language :: Python :: 3.9
Classifier: Programming Language :: Python :: 3.10
Classifier: Programming Language :: Python :: 3.11
Classifier: Programming Language :: Python :: Implementation :: CPython
Classifier: Programming Language :: Python :: Implementation :: PyPy
Requires-Python: >=3.7.0
License-File: LICENSE
